gitlab_exporter/__init__.py
gitlab_exporter/api.py
gitlab_exporter/gldates2ics.py
gitlab_exporter/issues2csv.py
gitlab_exporter/helpers/__init__.py
gitlab_exporter/helpers/gldates2ics.py
gitlab_exporter/helpers/issues2csv.py
gitlab_exporter-0.0.7.dist-info/LICENSE
gitlab_exporter-0.0.7.dist-info/METADATA
gitlab_exporter-0.0.7.dist-info/WHEEL
gitlab_exporter-0.0.7.dist-info/entry_points.txt
gitlab_exporter-0.0.7.dist-info/top_level.txt
gitlab_exporter-0.0.7.dist-info/RECORD
