Metadata-Version: 2.1
Name: gitlab-exporter
Version: 0.0.7
Summary: Export various data sets from GitLab issues, projects and groups
Home-page: https://collaborating.tuhh.de/hos/modernes-publizieren/offen/software/middleware/gitlab-exporter
Author: Axel Duerkop
Author-email: axel.duerkop@tuhh.de
License: UNKNOWN
Platform: UNKNOWN
Classifier: Programming Language :: Python :: 3
Classifier: License :: OSI Approved :: Apache Software License
Classifier: Operating System :: OS Independent
Requires-Python: >=3.6
Requires-Dist: astroid (>=2.1.0)
Requires-Dist: certifi (>=2018.11.29)
Requires-Dist: chardet (>=3.0.4)
Requires-Dist: icalendar (>=4.0.3)
Requires-Dist: idna (>=2.8)
Requires-Dist: isort (>=4.3.4)
Requires-Dist: lazy-object-proxy (>=1.3.1)
Requires-Dist: mccabe (>=0.6.1)
Requires-Dist: numpy (>=1.16.1)
Requires-Dist: pandas (>=0.24.1)
Requires-Dist: ply (>=3.11)
Requires-Dist: pypandoc (>=1.4)
Requires-Dist: python-dateutil (>=2.8.0)
Requires-Dist: python-gitlab (>=1.7.0)
Requires-Dist: pytz (>=2018.9)
Requires-Dist: requests (>=2.21.0)
Requires-Dist: six (>=1.12.0)
Requires-Dist: typed-ast (>=1.3.1)
Requires-Dist: urllib3 (>=1.24.1)
Requires-Dist: wrapt (>=1.11.1)
